Workbook
Name 商品マスタ: 商品マスタ!$A$4:$E$23
Name 税率: 設定!$B$4
Name シナリオ: 設定!$B$7

Sheet README
A1: 小売店の月次運営ブック
A3: このブックは Excelツール改修支援AI のデモ用サンプルです。
A5: シート構成
A7: 設定 | B7: 税率・為替・期間・シナリオを管理。Worksheet_Change で再計算
A8: 商品マスタ | B8: 20 商品の在庫・単価・カテゴリ。Excel テーブル化
A9: 日次売上 | B9: 30 日 × 商品の売上ログ (ピボットの元データ)
A10: シナリオ計算 | B10: シナリオに応じた予測。INDIRECT / OFFSET を使用
A11: ダッシュボード | B11: KPI と棒グラフ・折れ線。月次更新ボタン (VBA)
A12: PivotByCategory | B12: カテゴリ別売上集計 (SUMIFS 擬似ピボット)
A13: 月次レポート | B13: 印刷向け整形出力
A16: 改修例 (チャットで試せる質問)
A17: ・「税率を 10% から 12% に変えたとき、どこに波及しますか?」
A18: ・「カテゴリ『穀物』を 2 つに分割したい。どこを直す必要がありますか?」
A19: ・「日次売上を 60 日分に拡張したらシナリオ計算は追従しますか?」
A20: ・「INDIRECT を使っている箇所と、その実行時の参照先を一覧で」

Sheet 設定
A1: ブック設定
A3: 項目 | B3: 値 | C3: 備考 | E3: シナリオ別係数
A4: 税率 | B4: 0.1 | C4: 消費税率 | E4: シナリオ | F4: 売上係数
A5: 為替 (USD) | B5: 150 | C5: USD → JPY (月平均) | E5: 楽観 | F5: 1.15
A6: 集計期間 | B6: 標準 | C6: 30日 / 標準 / 60日 | E6: 標準 | F6: 1
A7: シナリオ | B7: 標準 | C7: 楽観 / 標準 / 悲観 (シナリオ計算が参照) | E7: 悲観 | F7: 0.85
A8: 最終更新 | B8: (未更新) | C8: Workbook_Open で自動更新
E9: (シナリオ計算!D2 が INDIRECT("設定!F"&MATCH(...)) で引く)

Sheet 商品マスタ
A1: 商品マスタ
A3: 商品コード | B3: 商品名 | C3: カテゴリ | D3: 単価 | E3: 在庫数
A4: P001 | B4: 白米 5kg | C4: 穀物 | D4: 1980 | E4: 120
A5: P002 | B5: 玄米 5kg | C5: 穀物 | D5: 2480 | E5: 60
A6: P003 | B6: もち米 2kg | C6: 穀物 | D6: 1280 | E6: 40
A7: P004 | B7: 雑穀ミックス 1kg | C7: 穀物 | D7: 1580 | E7: 90
A8: P005 | B8: 押し麦 800g | C8: 穀物 | D8: 780 | E8: 150
A9: P006 | B9: オートミール 500g | C9: 穀物 | D9: 680 | E9: 200
A10: P007 | B10: 黒米 500g | C10: 穀物 | D10: 1180 | E10: 25
A11: P008 | B11: 赤米 500g | C11: 穀物 | D11: 1280 | E11: 30
A12: P009 | B12: ハト麦 300g | C12: 穀物 | D12: 980 | E12: 45
A13: P010 | B13: 古代米セット | C13: 穀物 | D13: 2880 | E13: 15
A14: D001 | B14: 緑茶 200g | C14: 飲料 | D14: 980 | E14: 80
A15: D002 | B15: ほうじ茶 150g | C15: 飲料 | D15: 880 | E15: 70
... A23: C002 | B23: 本みりん 500ml | C23: 調味料 | D23: 980 | E23: 48

Sheet 日次売上
A1: 日次売上ログ
A3: 日付 | B3: 商品コード | C3: カテゴリ | D3: 数量 | E3: 売上金額 | F3: 担当者
A4: 46143 | B4: D004 | C4: 飲料 | D4: 1 | E4: 1480 | F4: 鈴木
A5: 46143 | B5: D002 | C5: 飲料 | D5: 9 | E5: 7920 | F5: 佐藤
A6: 46143 | B6: D003 | C6: 飲料 | D6: 6 | E6: 6480 | F6: 佐藤
A7: 46143 | B7: C001 | C7: 調味料 | D7: 9 | E7: 7020 | F7: 渡辺
A8: 46143 | B8: C002 | C8: 調味料 | D8: 2 | E8: 1960 | F8: 高橋
A9: 46143 | B9: P008 | C9: 穀物 | D9: 5 | E9: 6400 | F9: 田中
A10: 46144 | B10: D004 | C10: 飲料 | D10: 11 | E10: 16280 | F10: 佐藤
A11: 46144 | B11: P001 | C11: 穀物 | D11: 1 | E11: 1980 | F11: 渡辺
A12: 46144 | B12: P010 | C12: 穀物 | D12: 4 | E12: 11520 | F12: 高橋
A13: 46144 | B13: C001 | C13: 調味料 | D13: 10 | E13: 7800 | F13: 鈴木
A14: 46144 | B14: C002 | C14: 調味料 | D14: 3 | E14: 2940 | F14: 渡辺
A15: 46144 | B15: P008 | C15: 穀物 | D15: 8 | E15: 10240 | F15: 高橋
... A227: 46172 | B227: P007 | C227: 穀物 | D227: 7 | E227: 8260 | F227: 鈴木

Sheet シナリオ計算
A1: シナリオ別売上予測
A2: 選択中シナリオ: | B2: =設定!B7 | C2: 係数: | D2: =INDIRECT("設定!F"&(MATCH(B2,設定!E5:E7,0)+4))
A3: ↑ INDIRECT を使っているため、設定!F の構造が変わると壊れる
A5: 商品コード | B5: 商品名 | C5: 単価 | D5: 標準月販予測 | E5: シナリオ調整後 | F5: 在庫月数
A6: =商品マスタ!A4 | B6: =VLOOKUP(A6,商品マスタ!$A$4:$E$23,2,FALSE) | C6: =VLOOKUP(A6,商品マスタ!$A$4:$E$23,4,FALSE) | D6: =SUMIFS(日次売上!D:D,日次売上!B:B,A6) | E6: =D6*$D$2 | F6: =IF(D6=0,0,VLOOKUP(A6,商品マスタ!$A$4:$E$23,5,FALSE)/(SUM(OFFSET(日次売上!D4,0,0,COUNTA(日次売上!D:D)-1,1))/30))
A7: =商品マスタ!A5 | B7: =VLOOKUP(A7,商品マスタ!$A$4:$E$23,2,FALSE) | C7: =VLOOKUP(A7,商品マスタ!$A$4:$E$23,4,FALSE) | D7: =SUMIFS(日次売上!D:D,日次売上!B:B,A7) | E7: =D7*$D$2 | F7: =IF(D7=0,0,VLOOKUP(A7,商品マスタ!$A$4:$E$23,5,FALSE)/(SUM(OFFSET(日次売上!D4,0,0,COUNTA(日次売上!D:D)-1,1))/30))
A8: =商品マスタ!A6 | B8: =VLOOKUP(A8,商品マスタ!$A$4:$E$23,2,FALSE) | C8: =VLOOKUP(A8,商品マスタ!$A$4:$E$23,4,FALSE) | D8: =SUMIFS(日次売上!D:D,日次売上!B:B,A8) | E8: =D8*$D$2 | F8: =IF(D8=0,0,VLOOKUP(A8,商品マスタ!$A$4:$E$23,5,FALSE)/(SUM(OFFSET(日次売上!D4,0,0,COUNTA(日次売上!D:D)-1,1))/30))
A9: =商品マスタ!A7 | B9: =VLOOKUP(A9,商品マスタ!$A$4:$E$23,2,FALSE) | C9: =VLOOKUP(A9,商品マスタ!$A$4:$E$23,4,FALSE) | D9: =SUMIFS(日次売上!D:D,日次売上!B:B,A9) | E9: =D9*$D$2 | F9: =IF(D9=0,0,VLOOKUP(A9,商品マスタ!$A$4:$E$23,5,FALSE)/(SUM(OFFSET(日次売上!D4,0,0,COUNTA(日次売上!D:D)-1,1))/30))
A10: =商品マスタ!A8 | B10: =VLOOKUP(A10,商品マスタ!$A$4:$E$23,2,FALSE) | C10: =VLOOKUP(A10,商品マスタ!$A$4:$E$23,4,FALSE) | D10: =SUMIFS(日次売上!D:D,日次売上!B:B,A10) | E10: =D10*$D$2 | F10: =IF(D10=0,0,VLOOKUP(A10,商品マスタ!$A$4:$E$23,5,FALSE)/(SUM(OFFSET(日次売上!D4,0,0,COUNTA(日次売上!D:D)-1,1))/30))
A11: =商品マスタ!A9 | B11: =VLOOKUP(A11,商品マスタ!$A$4:$E$23,2,FALSE) | C11: =VLOOKUP(A11,商品マスタ!$A$4:$E$23,4,FALSE) | D11: =SUMIFS(日次売上!D:D,日次売上!B:B,A11) | E11: =D11*$D$2 | F11: =IF(D11=0,0,VLOOKUP(A11,商品マスタ!$A$4:$E$23,5,FALSE)/(SUM(OFFSET(日次売上!D4,0,0,COUNTA(日次売上!D:D)-1,1))/30))
A12: =商品マスタ!A10 | B12: =VLOOKUP(A12,商品マスタ!$A$4:$E$23,2,FALSE) | C12: =VLOOKUP(A12,商品マスタ!$A$4:$E$23,4,FALSE) | D12: =SUMIFS(日次売上!D:D,日次売上!B:B,A12) | E12: =D12*$D$2 | F12: =IF(D12=0,0,VLOOKUP(A12,商品マスタ!$A$4:$E$23,5,FALSE)/(SUM(OFFSET(日次売上!D4,0,0,COUNTA(日次売上!D:D)-1,1))/30))
A13: =商品マスタ!A11 | B13: =VLOOKUP(A13,商品マスタ!$A$4:$E$23,2,FALSE) | C13: =VLOOKUP(A13,商品マスタ!$A$4:$E$23,4,FALSE) | D13: =SUMIFS(日次売上!D:D,日次売上!B:B,A13) | E13: =D13*$D$2 | F13: =IF(D13=0,0,VLOOKUP(A13,商品マスタ!$A$4:$E$23,5,FALSE)/(SUM(OFFSET(日次売上!D4,0,0,COUNTA(日次売上!D:D)-1,1))/30))
A14: =商品マスタ!A12 | B14: =VLOOKUP(A14,商品マスタ!$A$4:$E$23,2,FALSE) | C14: =VLOOKUP(A14,商品マスタ!$A$4:$E$23,4,FALSE) | D14: =SUMIFS(日次売上!D:D,日次売上!B:B,A14) | E14: =D14*$D$2 | F14: =IF(D14=0,0,VLOOKUP(A14,商品マスタ!$A$4:$E$23,5,FALSE)/(SUM(OFFSET(日次売上!D4,0,0,COUNTA(日次売上!D:D)-1,1))/30))
A15: =商品マスタ!A13 | B15: =VLOOKUP(A15,商品マスタ!$A$4:$E$23,2,FALSE) | C15: =VLOOKUP(A15,商品マスタ!$A$4:$E$23,4,FALSE) | D15: =SUMIFS(日次売上!D:D,日次売上!B:B,A15) | E15: =D15*$D$2 | F15: =IF(D15=0,0,VLOOKUP(A15,商品マスタ!$A$4:$E$23,5,FALSE)/(SUM(OFFSET(日次売上!D4,0,0,COUNTA(日次売上!D:D)-1,1))/30))
A16: =商品マスタ!A14 | B16: =VLOOKUP(A16,商品マスタ!$A$4:$E$23,2,FALSE) | C16: =VLOOKUP(A16,商品マスタ!$A$4:$E$23,4,FALSE) | D16: =SUMIFS(日次売上!D:D,日次売上!B:B,A16) | E16: =D16*$D$2 | F16: =IF(D16=0,0,VLOOKUP(A16,商品マスタ!$A$4:$E$23,5,FALSE)/(SUM(OFFSET(日次売上!D4,0,0,COUNTA(日次売上!D:D)-1,1))/30))
A17: =商品マスタ!A15 | B17: =VLOOKUP(A17,商品マスタ!$A$4:$E$23,2,FALSE) | C17: =VLOOKUP(A17,商品マスタ!$A$4:$E$23,4,FALSE) | D17: =SUMIFS(日次売上!D:D,日次売上!B:B,A17) | E17: =D17*$D$2 | F17: =IF(D17=0,0,VLOOKUP(A17,商品マスタ!$A$4:$E$23,5,FALSE)/(SUM(OFFSET(日次売上!D4,0,0,COUNTA(日次売上!D:D)-1,1))/30))
A18: =商品マスタ!A16 | B18: =VLOOKUP(A18,商品マスタ!$A$4:$E$23,2,FALSE) | C18: =VLOOKUP(A18,商品マスタ!$A$4:$E$23,4,FALSE) | D18: =SUMIFS(日次売上!D:D,日次売上!B:B,A18) | E18: =D18*$D$2 | F18: =IF(D18=0,0,VLOOKUP(A18,商品マスタ!$A$4:$E$23,5,FALSE)/(SUM(OFFSET(日次売上!D4,0,0,COUNTA(日次売上!D:D)-1,1))/30))
A19: =商品マスタ!A17 | B19: =VLOOKUP(A19,商品マスタ!$A$4:$E$23,2,FALSE) | C19: =VLOOKUP(A19,商品マスタ!$A$4:$E$23,4,FALSE) | D19: =SUMIFS(日次売上!D:D,日次売上!B:B,A19) | E19: =D19*$D$2 | F19: =IF(D19=0,0,VLOOKUP(A19,商品マスタ!$A$4:$E$23,5,FALSE)/(SUM(OFFSET(日次売上!D4,0,0,COUNTA(日次売上!D:D)-1,1))/30))
A20: =商品マスタ!A18 | B20: =VLOOKUP(A20,商品マスタ!$A$4:$E$23,2,FALSE) | C20: =VLOOKUP(A20,商品マスタ!$A$4:$E$23,4,FALSE) | D20: =SUMIFS(日次売上!D:D,日次売上!B:B,A20) | E20: =D20*$D$2 | F20: =IF(D20=0,0,VLOOKUP(A20,商品マスタ!$A$4:$E$23,5,FALSE)/(SUM(OFFSET(日次売上!D4,0,0,COUNTA(日次売上!D:D)-1,1))/30))
A21: =商品マスタ!A19 | B21: =VLOOKUP(A21,商品マスタ!$A$4:$E$23,2,FALSE) | C21: =VLOOKUP(A21,商品マスタ!$A$4:$E$23,4,FALSE) | D21: =SUMIFS(日次売上!D:D,日次売上!B:B,A21) | E21: =D21*$D$2 | F21: =IF(D21=0,0,VLOOKUP(A21,商品マスタ!$A$4:$E$23,5,FALSE)/(SUM(OFFSET(日次売上!D4,0,0,COUNTA(日次売上!D:D)-1,1))/30))
A22: =商品マスタ!A20 | B22: =VLOOKUP(A22,商品マスタ!$A$4:$E$23,2,FALSE) | C22: =VLOOKUP(A22,商品マスタ!$A$4:$E$23,4,FALSE) | D22: =SUMIFS(日次売上!D:D,日次売上!B:B,A22) | E22: =D22*$D$2 | F22: =IF(D22=0,0,VLOOKUP(A22,商品マスタ!$A$4:$E$23,5,FALSE)/(SUM(OFFSET(日次売上!D4,0,0,COUNTA(日次売上!D:D)-1,1))/30))
A23: =商品マスタ!A21 | B23: =VLOOKUP(A23,商品マスタ!$A$4:$E$23,2,FALSE) | C23: =VLOOKUP(A23,商品マスタ!$A$4:$E$23,4,FALSE) | D23: =SUMIFS(日次売上!D:D,日次売上!B:B,A23) | E23: =D23*$D$2 | F23: =IF(D23=0,0,VLOOKUP(A23,商品マスタ!$A$4:$E$23,5,FALSE)/(SUM(OFFSET(日次売上!D4,0,0,COUNTA(日次売上!D:D)-1,1))/30))
A24: =商品マスタ!A22 | B24: =VLOOKUP(A24,商品マスタ!$A$4:$E$23,2,FALSE) | C24: =VLOOKUP(A24,商品マスタ!$A$4:$E$23,4,FALSE) | D24: =SUMIFS(日次売上!D:D,日次売上!B:B,A24) | E24: =D24*$D$2 | F24: =IF(D24=0,0,VLOOKUP(A24,商品マスタ!$A$4:$E$23,5,FALSE)/(SUM(OFFSET(日次売上!D4,0,0,COUNTA(日次売上!D:D)-1,1))/30))
A25: =商品マスタ!A23 | B25: =VLOOKUP(A25,商品マスタ!$A$4:$E$23,2,FALSE) | C25: =VLOOKUP(A25,商品マスタ!$A$4:$E$23,4,FALSE) | D25: =SUMIFS(日次売上!D:D,日次売上!B:B,A25) | E25: =D25*$D$2 | F25: =IF(D25=0,0,VLOOKUP(A25,商品マスタ!$A$4:$E$23,5,FALSE)/(SUM(OFFSET(日次売上!D4,0,0,COUNTA(日次売上!D:D)-1,1))/30))

Sheet PivotByCategory
A1: カテゴリ別月次集計
A2: (日次売上を SUMIFS でカテゴリ集計。Excel のピボットテーブルでも代替可)
A4: カテゴリ | B4: 売上金額 | C4: 数量 | D4: 客単価 (= 売上 / 数量)
A5: 穀物 | B5: =SUMIFS(日次売上!E:E,日次売上!C:C,A5) | C5: =SUMIFS(日次売上!D:D,日次売上!C:C,A5) | D5: =IF(C5=0,0,B5/C5)
A6: 飲料 | B6: =SUMIFS(日次売上!E:E,日次売上!C:C,A6) | C6: =SUMIFS(日次売上!D:D,日次売上!C:C,A6) | D6: =IF(C6=0,0,B6/C6)
A7: 乾物 | B7: =SUMIFS(日次売上!E:E,日次売上!C:C,A7) | C7: =SUMIFS(日次売上!D:D,日次売上!C:C,A7) | D7: =IF(C7=0,0,B7/C7)
A8: 調味料 | B8: =SUMIFS(日次売上!E:E,日次売上!C:C,A8) | C8: =SUMIFS(日次売上!D:D,日次売上!C:C,A8) | D8: =IF(C8=0,0,B8/C8)
A9: 合計 | B9: =SUM(B5:B8) | C9: =SUM(C5:C8)

Sheet ダッシュボード
A1: 月次ダッシュボード
A3: 総売上 | C3: 販売数量 | E3: 客単価 | G3: 在庫過剰商品
A4: =SUM(日次売上!E:E) | C4: =SUM(日次売上!D:D) | E4: =IFERROR(SUM(日次売上!E:E)/SUM(日次売上!D:D),0) | G4: =COUNTIF(シナリオ計算!F6:F100,">=6")
A7: カテゴリ別売上
A8: カテゴリ | B8: 売上
A9: 穀物 | B9: =PivotByCategory!B5
A10: 飲料 | B10: =PivotByCategory!B6
A11: 乾物 | B11: =PivotByCategory!B7
A12: 調味料 | B12: =PivotByCategory!B8
A16: 担当者別売上
A17: 担当者 | B17: 売上
A18: 田中 | B18: =SUMIFS(日次売上!E:E,日次売上!F:F,A18)
A19: 鈴木 | B19: =SUMIFS(日次売上!E:E,日次売上!F:F,A19)
A20: 佐藤 | B20: =SUMIFS(日次売上!E:E,日次売上!F:F,A20)
A21: 高橋 | B21: =SUMIFS(日次売上!E:E,日次売上!F:F,A21)
A22: 渡辺 | B22: =SUMIFS(日次売上!E:E,日次売上!F:F,A22)
A26: [ボタン: 月次更新] ← inject_vba.ps1 でフォームコントロールが追加され、MonthlyUpdate にリンクします

Sheet 月次レポート
A1: 月次運営レポート
A2: ="対象期間: "&設定!B6
A4: 総売上 | C4: 販売数量 | E4: 客単価
A5: =ダッシュボード!A4 | C5: =ダッシュボード!C4 | E5: =ダッシュボード!E4
A8: カテゴリ別内訳
A9: カテゴリ | B9: 売上金額 | C9: 数量 | D9: 客単価 | E9: 構成比
A10: 穀物 | B10: =PivotByCategory!B5 | C10: =PivotByCategory!C5 | D10: =PivotByCategory!D5 | E10: =IFERROR(B10/PivotByCategory!B9,0)
A11: 飲料 | B11: =PivotByCategory!B6 | C11: =PivotByCategory!C6 | D11: =PivotByCategory!D6 | E11: =IFERROR(B11/PivotByCategory!B10,0)
A12: 乾物 | B12: =PivotByCategory!B7 | C12: =PivotByCategory!C7 | D12: =PivotByCategory!D7 | E12: =IFERROR(B12/PivotByCategory!B11,0)
A13: 調味料 | B13: =PivotByCategory!B8 | C13: =PivotByCategory!C8 | D13: =PivotByCategory!D8 | E13: =IFERROR(B13/PivotByCategory!B12,0)
A16: 備考
A17: =" シナリオ: "&設定!B7&" / 税率: "&TEXT(設定!B4,"0.0%")
